{
    "Version": "1.1",
    "Data": {
        "Source": "f:\\code\\wolf engine 2.0\\wolf engine 2.0\\wolf engine 2.0\\vulkan.ixx",
        "ProvidedModule": "Vulkan",
        "Includes": [],
        "ImportedModules": [],
        "ImportedHeaderUnits": [
            {
                "Header": "f:\\code\\wolf engine 2.0\\wolf engine 2.0\\third party\\vulkan\\include\\vulkan\\vulkan.h",
                "BMI": "F:\\Code\\Wolf Engine 2.0\\Wolf Engine 2.0\\Wolf Engine 2.0\\x64\\Debug\\vulkan.h.ifc.dt"
            },
            {
                "Header": "f:\\code\\wolf engine 2.0\\wolf engine 2.0\\third party\\glfw\\include\\glfw\\glfw3.h",
                "BMI": "F:\\Code\\Wolf Engine 2.0\\Wolf Engine 2.0\\Wolf Engine 2.0\\x64\\Debug\\glfw3.h.ifc.dt"
            },
            {
                "Header": "f:\\code\\wolf engine 2.0\\wolf engine 2.0\\third party\\ovr\\include\\ovr_capi_vk.h",
                "BMI": "F:\\Code\\Wolf Engine 2.0\\Wolf Engine 2.0\\Wolf Engine 2.0\\x64\\Debug\\OVR_CAPI_Vk.h.ifc.dt"
            },
            {
                "Header": "c:\\program files (x86)\\microsoft visual studio\\2019\\enterprise\\vc\\tools\\msvc\\14.29.30133\\include\\mutex",
                "BMI": "F:\\Code\\Wolf Engine 2.0\\Wolf Engine 2.0\\Wolf Engine 2.0\\x64\\Debug\\mutex.ifc.dt"
            },
            {
                "Header": "c:\\program files (x86)\\microsoft visual studio\\2019\\enterprise\\vc\\tools\\msvc\\14.29.30133\\include\\vector",
                "BMI": "F:\\Code\\Wolf Engine 2.0\\Wolf Engine 2.0\\Wolf Engine 2.0\\x64\\Debug\\vector.ifc.dt"
            }
        ]
    }
}